relik/__init__.py
relik/version.py
relik/cli/__init__.py
relik/cli/cli.py
relik/cli/data.py
relik/cli/reader.py
relik/cli/retriever.py
relik/cli/utils.py
relik/common/__init__.py
relik/common/log.py
relik/common/torch_utils.py
relik/common/upload.py
relik/common/utils.py
relik/inference/__init__.py
relik/inference/annotator.py
relik/inference/utils.py
relik/inference/data/__init__.py
relik/inference/data/objects.py
relik/inference/data/splitters/__init__.py
relik/inference/data/splitters/base_sentence_splitter.py
relik/inference/data/splitters/blank_sentence_splitter.py
relik/inference/data/splitters/spacy_sentence_splitter.py
relik/inference/data/splitters/window_based_splitter.py
relik/inference/data/tokenizers/__init__.py
relik/inference/data/tokenizers/base_tokenizer.py
relik/inference/data/tokenizers/spacy_tokenizer.py
relik/inference/data/window/__init__.py
relik/inference/data/window/manager.py
relik/inference/serve/__init__.py
relik/inference/serve/backend/__init__.py
relik/inference/serve/backend/fastapi_be.py
relik/inference/serve/backend/ray.py
relik/inference/serve/backend/utils.py
relik/inference/serve/frontend/__init__.py
relik/inference/serve/frontend/gradio_fe.py
relik/inference/serve/frontend/relik_front.py
relik/inference/serve/frontend/relik_re_front.py
relik/inference/serve/frontend/utils.py
relik/reader/__init__.py
relik/reader/data/__init__.py
relik/reader/data/patches.py
relik/reader/data/relik_reader_data.py
relik/reader/data/relik_reader_data_utils.py
relik/reader/data/relik_reader_re_data.py
relik/reader/data/relik_reader_sample.py
relik/reader/lightning_modules/__init__.py
relik/reader/lightning_modules/relik_reader_pl_module.py
relik/reader/lightning_modules/relik_reader_re_pl_module.py
relik/reader/pytorch_modules/__init__.py
relik/reader/pytorch_modules/base.py
relik/reader/pytorch_modules/span.py
relik/reader/pytorch_modules/triplet.py
relik/reader/pytorch_modules/hf/__init__.py
relik/reader/pytorch_modules/hf/configuration_relik.py
relik-1.0.7.dist-info/METADATA
relik-1.0.7.dist-info/WHEEL
relik-1.0.7.dist-info/entry_points.txt
relik-1.0.7.dist-info/top_level.txt
relik-1.0.7.dist-info/RECORD
