Metadata-Version: 2.1
Name: relik
Version: 1.0.7
Summary: Fast and Accurate Entity Linking and Relation Extraction on an Academic Budget
Home-page: https://github.com/SapienzaNLP/relik
Author: Edoardo Barba, Riccardo Orlando, Pere-Lluís Huguet Cabot
Author-email: orlandorcc@gmail.com
License: Apache
Keywords: NLP Sapienza sapienzanlp deep learning transformer pytorch retriever entity linking relation extraction reader budget
Classifier: Intended Audience :: Science/Research
Classifier: License :: OSI Approved :: Apache Software License
Classifier: Programming Language :: Python :: 3
Classifier: Topic :: Scientific/Engineering :: Artificial Intelligence
Requires-Python: >=3.10,<3.12
Requires-Dist: torch ==2.3.1
Requires-Dist: transformers[sentencepiece] <4.42,>=4.41
Requires-Dist: rich <14.0.0,>=13.0.0
Requires-Dist: scikit-learn <1.6,>=1.5
Requires-Dist: overrides <7.9,>=7.4
Requires-Dist: art ==6.2
Requires-Dist: pprintpp ==0.4.0
Requires-Dist: colorama ==0.4.6
Requires-Dist: termcolor ==2.4.0
Requires-Dist: spacy <3.8,>=3.7
Requires-Dist: typer <0.13,>=0.12
Requires-Dist: lightning <2.4,>=2.3
Requires-Dist: datasets <2.15,>=2.13
Requires-Dist: hydra-core <1.4,>=1.3
Requires-Dist: hydra-colorlog
Requires-Dist: wandb <0.18,>=0.15
Provides-Extra: all
Requires-Dist: faiss-cpu ==1.8.0 ; extra == 'all'
Requires-Dist: fastapi <0.113,>=0.112 ; extra == 'all'
Requires-Dist: uvicorn[standard] ==0.23.2 ; extra == 'all'
Requires-Dist: gunicorn ==22.0.0 ; extra == 'all'
Requires-Dist: streamlit <1.29,>=1.28 ; extra == 'all'
Requires-Dist: streamlit-extras <0.4,>=0.3 ; extra == 'all'
Requires-Dist: gradio <4.38,>=4.37 ; extra == 'all'
Requires-Dist: pyvis ; extra == 'all'
Requires-Dist: ray[serve] <=2.35,>=2.34 ; extra == 'all'
Requires-Dist: pre-commit ; extra == 'all'
Requires-Dist: black[d] ; extra == 'all'
Requires-Dist: isort ; extra == 'all'
Provides-Extra: dev
Requires-Dist: pre-commit ; extra == 'dev'
Requires-Dist: black[d] ; extra == 'dev'
Requires-Dist: isort ; extra == 'dev'
Provides-Extra: faiss
Requires-Dist: faiss-cpu ==1.8.0 ; extra == 'faiss'
Provides-Extra: ray
Requires-Dist: fastapi <0.113,>=0.112 ; extra == 'ray'
Requires-Dist: uvicorn[standard] ==0.23.2 ; extra == 'ray'
Requires-Dist: gunicorn ==22.0.0 ; extra == 'ray'
Requires-Dist: streamlit <1.29,>=1.28 ; extra == 'ray'
Requires-Dist: streamlit-extras <0.4,>=0.3 ; extra == 'ray'
Requires-Dist: gradio <4.38,>=4.37 ; extra == 'ray'
Requires-Dist: pyvis ; extra == 'ray'
Requires-Dist: ray[serve] <=2.35,>=2.34 ; extra == 'ray'
Provides-Extra: serve
Requires-Dist: fastapi <0.113,>=0.112 ; extra == 'serve'
Requires-Dist: uvicorn[standard] ==0.23.2 ; extra == 'serve'
Requires-Dist: gunicorn ==22.0.0 ; extra == 'serve'
Requires-Dist: streamlit <1.29,>=1.28 ; extra == 'serve'
Requires-Dist: streamlit-extras <0.4,>=0.3 ; extra == 'serve'
Requires-Dist: gradio <4.38,>=4.37 ; extra == 'serve'
Requires-Dist: pyvis ; extra == 'serve'
